MANIFEST.in
README.txt
ilrt.migrationtool-configure.zcml
setup.cfg
setup.py
docs/HISTORY.txt
docs/INSTALL.txt
docs/LICENSE.BSD
docs/LICENSE.txt
docs/TODO.txt
docs/migrations/__init__.py
docs/migrations/migration1.py
ilrt/__init__.py
ilrt.migrationtool.egg-info/PKG-INFO
ilrt.migrationtool.egg-info/SOURCES.txt
ilrt.migrationtool.egg-info/dependency_links.txt
ilrt.migrationtool.egg-info/entry_points.txt
ilrt.migrationtool.egg-info/namespace_packages.txt
ilrt.migrationtool.egg-info/not-zip-safe
ilrt.migrationtool.egg-info/paster_plugins.txt
ilrt.migrationtool.egg-info/requires.txt
ilrt.migrationtool.egg-info/top_level.txt
ilrt/migrationtool/__init__.py
ilrt/migrationtool/configure.zcml
ilrt/migrationtool/profiles.zcml
ilrt/migrationtool/version.txt
ilrt/migrationtool/browser/__init__.py
ilrt/migrationtool/browser/atfieldtool.py
ilrt/migrationtool/browser/configure.zcml
ilrt/migrationtool/browser/interfaces.py
ilrt/migrationtool/browser/migrationtool.py
ilrt/migrationtool/browser/utils.py
ilrt/migrationtool/browser/workflowtool.py
ilrt/migrationtool/browser/templates/help.pt
ilrt/migrationtool/browser/templates/manage_workflow.pt
ilrt/migrationtool/browser/templates/migrationResults.pt
ilrt/migrationtool/browser/templates/migrationRun.pt
ilrt/migrationtool/browser/templates/migrationRunMethod.pt
ilrt/migrationtool/browser/templates/migrationTool.pt
ilrt/migrationtool/profiles/default/toolset.xml
ilrt/migrationtool/tests/__init__.py
ilrt/migrationtool/tests/atfitool.txt
ilrt/migrationtool/tests/base.py
ilrt/migrationtool/tests/browsertool.txt
ilrt/migrationtool/tests/migrationtool.txt
ilrt/migrationtool/tests/test_migrationtool.py
ilrt/migrationtool/tests/utils.txt
ilrt/migrationtool/tests/workflowtool.txt