Metadata-Version: 1.0
Name: ilrt.migrationtool
Version: 0.4
Summary: A site migration tool for Plone that uses the site's theme egg version releases
Home-page: https://svn.ilrt.bris.ac.uk/repos/pypi/ilrt.migrationtool
Author: Internet Development, ILRT, University of Bristol
Author-email: internet-development@bris.ac.uk
License: GPL
Keywords: web zope plone migration setup release management workflow
Platform: UNKNOWN
Classifier: Programming Language :: Python
Classifier: Topic :: Software Development :: Libraries :: Python Modules
Classifier: Environment :: Web Environment
Classifier: Framework :: Plone
Classifier: Framework :: Zope2
Classifier: Framework :: Zope3
Classifier: Intended Audience :: Developers
Classifier: Intended Audience :: Other Audience
Classifier: License :: OSI Approved :: BSD License
Classifier: Operating System :: OS Independent
Classifier: Development Status :: 4 - Beta
